beautifuljason/__init__.py
beautifuljason/base.py
beautifuljason/data.py
beautifuljason/document.py
beautifuljason/graphics.py
beautifuljason/jason.py
beautifuljason/utils.py
beautifuljason/examples/JEOL_company_logo.png
beautifuljason/examples/__init__.py
beautifuljason/examples/analyze_and_report.py
beautifuljason/examples/quick_start.py
beautifuljason/tests/__init__.py
beautifuljason/tests/config.py
beautifuljason/tests/test_base.py
beautifuljason/tests/test_data.py
beautifuljason/tests/test_document.py
beautifuljason/tests/test_graphics.py
beautifuljason/tests/test_jason.py
beautifuljason/tests/test_utils.py
beautifuljason/tests/data/Ethylindanone_Carbon-3-1.jdf
beautifuljason/tests/data/Ethylindanone_HMQC-1-1.jdf
beautifuljason/tests/data/Ethylindanone_Proton+Carbon+HMQC.jjh5
beautifuljason/tests/data/Ethylindanone_Proton-13-1 (chart sum integral vs peak area).jjh5
beautifuljason/tests/data/Ethylindanone_Proton-13-1.jdf
beautifuljason/tests/data/Ethylindanone_Proton-13-1.jjh5
beautifuljason/tests/data/Ethylindanone_Proton-13-1_with_annotations.jjh5
beautifuljason/tests/data/Ethylindanone_Proton-13-1_with_multiplet_reports.jjh5
beautifuljason/tests/data/Ethylindanone_Proton-13-1_with_tables(parameters+multiplets).jjh5
beautifuljason/tests/data/Ethylindanone_Proton-13-1_with_tables.jjh5
beautifuljason/tests/data/Ethylindanone_Proton-13-1_with_tables_v2.jjh5
beautifuljason/tests/data/Ethylindanone_hsqc-2-1.jjh5
beautifuljason/tests/data/Ethylindanone_molecule.jjh5
beautifuljason/tests/data/Ethylindanone_molecule_with_assignment_table.jjh5
beautifuljason/tests/data/JEOL_company_logo.jjh5
beautifuljason/tests/data/cahe_Proton-14-1_with_peak_table.jjh5
beautifuljason/tests/data/cahe_cpmg-1-1.jjh5
beautifuljason/tests/data/empty.jjh5
beautifuljason/tests/data/jason_logo.png
beautifuljason/tests/data/lorem_ipsum.jjh5
beautifuljason/tools/__init__.py
beautifuljason/tools/batch_extract_integrals.py
beautifuljason/tools/jason_batch_convert.py
beautifuljason-1.1.1.dist-info/entry_points.txt
beautifuljason-1.1.1.dist-info/licenses/LICENSE
beautifuljason-1.1.1.dist-info/WHEEL
beautifuljason-1.1.1.dist-info/METADATA
beautifuljason-1.1.1.dist-info/RECORD
